converter/__init__.py
converter/converter.py
converter/converter_config.py
executor/__init__.py
executor/executor.py
executor/executor_config.py
library/__init__.py
library/aws_service.py
library/common.py
library/exceptions.py
library/kafka_service.py
library/logger.py
model/__init__.py
model/request_model.py
model/response_model.py
result/__init__.py
result/generator.py
result/result_config.py
result/result_formatter.py
result/result_mapper.py
result/result_producer.py
source/__init__.py
source/source_config.py
source/source_formatter.py
source/source_mapper.py
validator/__init__.py
validator/validator.py
validator/validator_config.py
fixedwidth_transformer-0.0.1.post1627218962.dist-info/LICENSE
fixedwidth_transformer-0.0.1.post1627218962.dist-info/METADATA
fixedwidth_transformer-0.0.1.post1627218962.dist-info/WHEEL
fixedwidth_transformer-0.0.1.post1627218962.dist-info/top_level.txt
fixedwidth_transformer-0.0.1.post1627218962.dist-info/RECORD
