Metadata-Version: 2.1
Name: fixedwidth-transformer
Version: 0.0.1.post1627218962
Summary: UNKNOWN
Home-page: https://github.com/SimpleConstructs/fixed-width-transformer
Author: Simple Constructs
Author-email: simpleconstructsyt@gmail.com
License: UNKNOWN
Project-URL: Bug Tracker, https://github.com/SimpleConstructs/fixed-width-transformer/issues
Project-URL: Documentation, https://fixed-width-transformer.readthedocs.io/en/latest/
Platform: UNKNOWN
Classifier: Programming Language :: Python :: 3
Classifier: License :: OSI Approved :: MIT License
Classifier: Operating System :: OS Independent
Requires-Python: >=3
License-File: LICENSE
